{
  "version": "2.0",
  "exportDate": "2025-10-21T10:00:00.000Z",
  "championshipName": "Test_Mode_Poules",
  "championship": {
    "currentDay": 1,
    "config": {
      "numDivisions": 3,
      "numCourts": 4
    },
    "days": {
    "1": {
      "players": {
        "1": [
          "Alice Martin",
          "Bob Durand",
          "Charlie Dubois",
          "David Laurent",
          "Emma Rousseau",
          "Felix Blanc",
          "Giselle Noir",
          "Hugo Vert"
        ],
        "2": [
          "Isabelle Jaune",
          "Jules Rouge",
          "Karine Bleu",
          "Louis Orange",
          "Marie Violet",
          "Nathan Rose",
          "Oceane Gris",
          "Pierre Marron"
        ],
        "3": [
          "Quentin Argent",
          "Rose Dore",
          "Simon Cuivre",
          "Therese Bronze",
          "Ulysse Acier",
          "Valerie Ivoire",
          "William Sable",
          "Xavier Perle"
        ]
      },
      "matches": {
        "1": [],
        "2": [],
        "3": []
      },
      "pools": {
        "enabled": true,
        "divisions": {
          "1": {
            "pools": [
              ["Alice Martin", "Bob Durand", "Charlie Dubois", "David Laurent"],
              ["Emma Rousseau", "Felix Blanc", "Giselle Noir", "Hugo Vert"]
            ],
            "matches": [
              {
                "id": 0,
                "player1": "Alice Martin",
                "player2": "Bob Durand",
                "poolIndex": 0,
                "poolName": "Poule A",
                "division": 1,
                "dayNumber": 1,
                "score1": "11",
                "score2": "8",
                "completed": true,
                "winner": "Alice Martin",
                "isPoolMatch": true
              },
              {
                "id": 1,
                "player1": "Alice Martin",
                "player2": "Charlie Dubois",
                "poolIndex": 0,
                "poolName": "Poule A",
                "division": 1,
                "dayNumber": 1,
                "score1": "11",
                "score2": "9",
                "completed": true,
                "winner": "Alice Martin",
                "isPoolMatch": true
              },
              {
                "id": 2,
                "player1": "Alice Martin",
                "player2": "David Laurent",
                "poolIndex": 0,
                "poolName": "Poule A",
                "division": 1,
                "dayNumber": 1,
                "score1": "11",
                "score2": "7",
                "completed": true,
                "winner": "Alice Martin",
                "isPoolMatch": true
              },
              {
                "id": 3,
                "player1": "Bob Durand",
                "player2": "Charlie Dubois",
                "poolIndex": 0,
                "poolName": "Poule A",
                "division": 1,
                "dayNumber": 1,
                "score1": "11",
                "score2": "6",
                "completed": true,
                "winner": "Bob Durand",
                "isPoolMatch": true
              },
              {
                "id": 4,
                "player1": "Bob Durand",
                "player2": "David Laurent",
                "poolIndex": 0,
                "poolName": "Poule A",
                "division": 1,
                "dayNumber": 1,
                "score1": "11",
                "score2": "10",
                "completed": true,
                "winner": "Bob Durand",
                "isPoolMatch": true
              },
              {
                "id": 5,
                "player1": "Charlie Dubois",
                "player2": "David Laurent",
                "poolIndex": 0,
                "poolName": "Poule A",
                "division": 1,
                "dayNumber": 1,
                "score1": "11",
                "score2": "9",
                "completed": true,
                "winner": "Charlie Dubois",
                "isPoolMatch": true
              },
              {
                "id": 6,
                "player1": "Emma Rousseau",
                "player2": "Felix Blanc",
                "poolIndex": 1,
                "poolName": "Poule B",
                "division": 1,
                "dayNumber": 1,
                "score1": "11",
                "score2": "7",
                "completed": true,
                "winner": "Emma Rousseau",
                "isPoolMatch": true
              },
              {
                "id": 7,
                "player1": "Emma Rousseau",
                "player2": "Giselle Noir",
                "poolIndex": 1,
                "poolName": "Poule B",
                "division": 1,
                "dayNumber": 1,
                "score1": "11",
                "score2": "8",
                "completed": true,
                "winner": "Emma Rousseau",
                "isPoolMatch": true
              },
              {
                "id": 8,
                "player1": "Emma Rousseau",
                "player2": "Hugo Vert",
                "poolIndex": 1,
                "poolName": "Poule B",
                "division": 1,
                "dayNumber": 1,
                "score1": "11",
                "score2": "6",
                "completed": true,
                "winner": "Emma Rousseau",
                "isPoolMatch": true
              },
              {
                "id": 9,
                "player1": "Felix Blanc",
                "player2": "Giselle Noir",
                "poolIndex": 1,
                "poolName": "Poule B",
                "division": 1,
                "dayNumber": 1,
                "score1": "11",
                "score2": "9",
                "completed": true,
                "winner": "Felix Blanc",
                "isPoolMatch": true
              },
              {
                "id": 10,
                "player1": "Felix Blanc",
                "player2": "Hugo Vert",
                "poolIndex": 1,
                "poolName": "Poule B",
                "division": 1,
                "dayNumber": 1,
                "score1": "11",
                "score2": "10",
                "completed": true,
                "winner": "Felix Blanc",
                "isPoolMatch": true
              },
              {
                "id": 11,
                "player1": "Giselle Noir",
                "player2": "Hugo Vert",
                "poolIndex": 1,
                "poolName": "Poule B",
                "division": 1,
                "dayNumber": 1,
                "score1": "11",
                "score2": "8",
                "completed": true,
                "winner": "Giselle Noir",
                "isPoolMatch": true
              }
            ],
            "finalPhase": []
          },
          "2": {
            "pools": [
              ["Isabelle Jaune", "Jules Rouge", "Karine Bleu", "Louis Orange"],
              ["Marie Violet", "Nathan Rose", "Oceane Gris", "Pierre Marron"]
            ],
            "matches": [
              {
                "id": 0,
                "player1": "Isabelle Jaune",
                "player2": "Jules Rouge",
                "poolIndex": 0,
                "poolName": "Poule A",
                "division": 2,
                "dayNumber": 1,
                "score1": "11",
                "score2": "7",
                "completed": true,
                "winner": "Isabelle Jaune",
                "isPoolMatch": true
              },
              {
                "id": 1,
                "player1": "Isabelle Jaune",
                "player2": "Karine Bleu",
                "poolIndex": 0,
                "poolName": "Poule A",
                "division": 2,
                "dayNumber": 1,
                "score1": "11",
                "score2": "8",
                "completed": true,
                "winner": "Isabelle Jaune",
                "isPoolMatch": true
              },
              {
                "id": 2,
                "player1": "Isabelle Jaune",
                "player2": "Louis Orange",
                "poolIndex": 0,
                "poolName": "Poule A",
                "division": 2,
                "dayNumber": 1,
                "score1": "11",
                "score2": "6",
                "completed": true,
                "winner": "Isabelle Jaune",
                "isPoolMatch": true
              },
              {
                "id": 3,
                "player1": "Jules Rouge",
                "player2": "Karine Bleu",
                "poolIndex": 0,
                "poolName": "Poule A",
                "division": 2,
                "dayNumber": 1,
                "score1": "11",
                "score2": "9",
                "completed": true,
                "winner": "Jules Rouge",
                "isPoolMatch": true
              },
              {
                "id": 4,
                "player1": "Jules Rouge",
                "player2": "Louis Orange",
                "poolIndex": 0,
                "poolName": "Poule A",
                "division": 2,
                "dayNumber": 1,
                "score1": "11",
                "score2": "10",
                "completed": true,
                "winner": "Jules Rouge",
                "isPoolMatch": true
              },
              {
                "id": 5,
                "player1": "Karine Bleu",
                "player2": "Louis Orange",
                "poolIndex": 0,
                "poolName": "Poule A",
                "division": 2,
                "dayNumber": 1,
                "score1": "11",
                "score2": "8",
                "completed": true,
                "winner": "Karine Bleu",
                "isPoolMatch": true
              },
              {
                "id": 6,
                "player1": "Marie Violet",
                "player2": "Nathan Rose",
                "poolIndex": 1,
                "poolName": "Poule B",
                "division": 2,
                "dayNumber": 1,
                "score1": "11",
                "score2": "6",
                "completed": true,
                "winner": "Marie Violet",
                "isPoolMatch": true
              },
              {
                "id": 7,
                "player1": "Marie Violet",
                "player2": "Oceane Gris",
                "poolIndex": 1,
                "poolName": "Poule B",
                "division": 2,
                "dayNumber": 1,
                "score1": "11",
                "score2": "7",
                "completed": true,
                "winner": "Marie Violet",
                "isPoolMatch": true
              },
              {
                "id": 8,
                "player1": "Marie Violet",
                "player2": "Pierre Marron",
                "poolIndex": 1,
                "poolName": "Poule B",
                "division": 2,
                "dayNumber": 1,
                "score1": "11",
                "score2": "5",
                "completed": true,
                "winner": "Marie Violet",
                "isPoolMatch": true
              },
              {
                "id": 9,
                "player1": "Nathan Rose",
                "player2": "Oceane Gris",
                "poolIndex": 1,
                "poolName": "Poule B",
                "division": 2,
                "dayNumber": 1,
                "score1": "11",
                "score2": "8",
                "completed": true,
                "winner": "Nathan Rose",
                "isPoolMatch": true
              },
              {
                "id": 10,
                "player1": "Nathan Rose",
                "player2": "Pierre Marron",
                "poolIndex": 1,
                "poolName": "Poule B",
                "division": 2,
                "dayNumber": 1,
                "score1": "11",
                "score2": "9",
                "completed": true,
                "winner": "Nathan Rose",
                "isPoolMatch": true
              },
              {
                "id": 11,
                "player1": "Oceane Gris",
                "player2": "Pierre Marron",
                "poolIndex": 1,
                "poolName": "Poule B",
                "division": 2,
                "dayNumber": 1,
                "score1": "11",
                "score2": "7",
                "completed": true,
                "winner": "Oceane Gris",
                "isPoolMatch": true
              }
            ],
            "finalPhase": []
          },
          "3": {
            "pools": [
              ["Quentin Argent", "Rose Dore", "Simon Cuivre", "Therese Bronze"],
              ["Ulysse Acier", "Valerie Ivoire", "William Sable", "Xavier Perle"]
            ],
            "matches": [
              {
                "id": 0,
                "player1": "Quentin Argent",
                "player2": "Rose Dore",
                "poolIndex": 0,
                "poolName": "Poule A",
                "division": 3,
                "dayNumber": 1,
                "score1": "11",
                "score2": "6",
                "completed": true,
                "winner": "Quentin Argent",
                "isPoolMatch": true
              },
              {
                "id": 1,
                "player1": "Quentin Argent",
                "player2": "Simon Cuivre",
                "poolIndex": 0,
                "poolName": "Poule A",
                "division": 3,
                "dayNumber": 1,
                "score1": "11",
                "score2": "7",
                "completed": true,
                "winner": "Quentin Argent",
                "isPoolMatch": true
              },
              {
                "id": 2,
                "player1": "Quentin Argent",
                "player2": "Therese Bronze",
                "poolIndex": 0,
                "poolName": "Poule A",
                "division": 3,
                "dayNumber": 1,
                "score1": "11",
                "score2": "5",
                "completed": true,
                "winner": "Quentin Argent",
                "isPoolMatch": true
              },
              {
                "id": 3,
                "player1": "Rose Dore",
                "player2": "Simon Cuivre",
                "poolIndex": 0,
                "poolName": "Poule A",
                "division": 3,
                "dayNumber": 1,
                "score1": "11",
                "score2": "8",
                "completed": true,
                "winner": "Rose Dore",
                "isPoolMatch": true
              },
              {
                "id": 4,
                "player1": "Rose Dore",
                "player2": "Therese Bronze",
                "poolIndex": 0,
                "poolName": "Poule A",
                "division": 3,
                "dayNumber": 1,
                "score1": "11",
                "score2": "9",
                "completed": true,
                "winner": "Rose Dore",
                "isPoolMatch": true
              },
              {
                "id": 5,
                "player1": "Simon Cuivre",
                "player2": "Therese Bronze",
                "poolIndex": 0,
                "poolName": "Poule A",
                "division": 3,
                "dayNumber": 1,
                "score1": "11",
                "score2": "7",
                "completed": true,
                "winner": "Simon Cuivre",
                "isPoolMatch": true
              },
              {
                "id": 6,
                "player1": "Ulysse Acier",
                "player2": "Valerie Ivoire",
                "poolIndex": 1,
                "poolName": "Poule B",
                "division": 3,
                "dayNumber": 1,
                "score1": "11",
                "score2": "5",
                "completed": true,
                "winner": "Ulysse Acier",
                "isPoolMatch": true
              },
              {
                "id": 7,
                "player1": "Ulysse Acier",
                "player2": "William Sable",
                "poolIndex": 1,
                "poolName": "Poule B",
                "division": 3,
                "dayNumber": 1,
                "score1": "11",
                "score2": "6",
                "completed": true,
                "winner": "Ulysse Acier",
                "isPoolMatch": true
              },
              {
                "id": 8,
                "player1": "Ulysse Acier",
                "player2": "Xavier Perle",
                "poolIndex": 1,
                "poolName": "Poule B",
                "division": 3,
                "dayNumber": 1,
                "score1": "11",
                "score2": "4",
                "completed": true,
                "winner": "Ulysse Acier",
                "isPoolMatch": true
              },
              {
                "id": 9,
                "player1": "Valerie Ivoire",
                "player2": "William Sable",
                "poolIndex": 1,
                "poolName": "Poule B",
                "division": 3,
                "dayNumber": 1,
                "score1": "11",
                "score2": "7",
                "completed": true,
                "winner": "Valerie Ivoire",
                "isPoolMatch": true
              },
              {
                "id": 10,
                "player1": "Valerie Ivoire",
                "player2": "Xavier Perle",
                "poolIndex": 1,
                "poolName": "Poule B",
                "division": 3,
                "dayNumber": 1,
                "score1": "11",
                "score2": "8",
                "completed": true,
                "winner": "Valerie Ivoire",
                "isPoolMatch": true
              },
              {
                "id": 11,
                "player1": "William Sable",
                "player2": "Xavier Perle",
                "poolIndex": 1,
                "poolName": "Poule B",
                "division": 3,
                "dayNumber": 1,
                "score1": "11",
                "score2": "6",
                "completed": true,
                "winner": "William Sable",
                "isPoolMatch": true
              }
            ],
            "finalPhase": []
          }
        }
      }
    }
  }
  },
  "stats": {
    "totalPlayers": 24,
    "totalMatches": 36,
    "totalDays": 1,
    "uniquePlayersList": [
      "Alice Martin",
      "Bob Durand",
      "Charlie Dubois",
      "David Laurent",
      "Emma Rousseau",
      "Felix Blanc",
      "Giselle Noir",
      "Hugo Vert",
      "Isabelle Jaune",
      "Jules Rouge",
      "Karine Bleu",
      "Louis Orange",
      "Marie Violet",
      "Nathan Rose",
      "Oceane Gris",
      "Pierre Marron",
      "Quentin Argent",
      "Rose Dore",
      "Simon Cuivre",
      "Therese Bronze",
      "Ulysse Acier",
      "Valerie Ivoire",
      "William Sable",
      "Xavier Perle"
    ]
  }
}
